{
  "name": "Edward Fox",
  "age": 34,
  "address": {
    "street": "Iweem Highway",
    "city": "Nikitat",
    "state": "NM",
    "zip": "49204"
  },
  "contact": {
    "phone": "(978) 590-1844",
    "servicePhone": "800778394"
  },
  "birthday": "1984-06-20T21:44:05.061Z",
  "ip": "202.158.23.170",
  "foo": "bar",
  "profile": {
    "about": "Wevtivel jo ru imbek zegafadi muaje waipi kiwujbu dijnon so hefopcab se arwejif vuk ip jozbawuc. Wowewmor nedo zegut neoj ifibo ronwo biomemo voz awra kiip sacjuk kuiz kuzcowu. Ih omi zevev je bosfe ba leerfif noopiro divo rodog lufdapig ursaska ruluine deijiufo wiz ruluv. Ewcafas dofkug tukmavwu hiwiin ver bihosuras otu zec kuejoga jawli pub fosiku cubmiez ejwoumu. Jup du coni omegfa ro vufupnuj dipeba je sakimu ula tiepepo zunovhon ur.",
    "bio": "Gehiwoup li orcujwa lizuima fes cuc bacomela subizan kiwat hohafad ficjit ti das ukfaab boromne got zemelcom nilic. Re gakuk nis nu bav tiowe anucakguw mugrewse if zazfupu nipobip udehupve gute ge ilifobus rez. Gahugo zuwih rub luoro mo vobre meakufol ut ad wiw ejo ef wu ezocib pazil damidgoh miesa havikbo. Ba go ceucba fu gofe ogi umu nar rotienu hakgu ca nevu li."
  },
  "apiKey": "b4602469972b5c54a5abd2083892cb0802d13b09969126408e91e81eedfc05dd",
  "currency": {
    "code": "BSD",
    "name": "Bahamas Dollar"
  }
}