{
  "name": "Viola Diaz",
  "age": 50,
  "address": {
    "street": "Jelij Way",
    "city": "Saleug",
    "state": "TX",
    "zip": "00874"
  },
  "contact": {
    "phone": "(935) 437-8123",
    "servicePhone": "800824555"
  },
  "birthday": "2005-10-31T12:02:12.951Z",
  "ip": "85.1.187.207",
  "foo": "bar",
  "profile": {
    "about": "Wad ocficoh viccos lumik jotsa bagipami lomiiha caufofi zib nit iwuaro tiptujci hofedkit bedu nag pa. Bibgaj fuj zalku puone davotu pifap eccekri wabiw numcueh uzojig pungo pophum. Ninhit ufteruzo ve hin vaw lo kez uhitoc mut puzciz cueki pu jihcuvow huhiv jaafesi wezdipruv jolpa da. Tuf zonli pubun li esi opu vi uciri zol dizsihco il cotuluzo temocot apceh vatulte ce ze. Kulvava jibos kanve juico uduni ok peejooh uhiefho ori vu sim penapwa tu pid tot ko vepitu.",
    "bio": "Mooc bar umupeso pu molmacij piw oduruid vewjuate ireoh mizozi momreh pukolur zacahcub esimurpa. Hutfafid ati gib nutepi odaguab lir firiske ajeig lig lozwupac cugkeasi ubikabes wijruha fo. Junfe davsa evobamo tuibke sas ja becbof ro maabo hipopi visa vi zut dil tikdumo gujas. Buk sukevahaf lutped ricaw ennezkag leloktu bunibaza udusevez ut tagfeke govmi obbe. Ratadlaz ralwer om wimiw nokodul hojihi cefhoj eraritoc re somucfa lirmu nefu."
  },
  "apiKey": "673803a291d17e65a88368da3d13dda18a720d6a4b49dbcff0f8311b4d91ad4e",
  "currency": {
    "code": "SGD",
    "name": "Singapore Dollar"
  }
}